markdown_kernel/__init__.py
markdown_kernel/_version.py
markdown_kernel/install.py
markdown_kernel/kernel.py
markdown_kernel/logo-64x64.png
markdown_kernel-0.2.2.dist-info/LICENSE
markdown_kernel-0.2.2.dist-info/METADATA
markdown_kernel-0.2.2.dist-info/WHEEL
markdown_kernel-0.2.2.dist-info/top_level.txt
markdown_kernel-0.2.2.dist-info/RECORD
