Metadata-Version: 2.1
Name: markdown-kernel
Version: 0.2.2
Summary: A markdown kernel for Jupyter
Home-page: https://github.com/vatlab/markdown-kernel
Author: Bo Peng
Author-email: bpeng@mdanderson.org
Maintainer: Bo Peng
Maintainer-email: bpeng@mdanderson.org
License: 3-clause BSD
Platform: UNKNOWN
Classifier: Development Status :: 4 - Beta
Classifier: Environment :: Console
Classifier: License :: OSI Approved :: BSD License
Classifier: Natural Language :: English
Classifier: Operating System :: POSIX :: Linux
Classifier: Operating System :: MacOS :: MacOS X
Classifier: Operating System :: Microsoft :: Windows
Classifier: Intended Audience :: Information Technology
Classifier: Intended Audience :: Science/Research
Classifier: Programming Language :: Python :: 3 :: Only
Classifier: Programming Language :: Python :: Implementation :: CPython
Requires-Dist: notebook
Requires-Dist: markdown
